[
    {
        "jeepsyHId": "jh1",
        "images": [
            "/carProduct/carshelter1.jpg",
            "/carProduct/carshelter2.jpg",
            "/carProduct/carshelter3.jpg"
        ],
        "name": "Jeepsy Half 1",
        "description": "Car shelter description for Shelter 1."
    },
    {
        "jeepsyHId": "jh2",
        "images": [
            "/carProduct/carshelter2.jpg",
            "/carProduct/carshelter1.jpg",
            "/carProduct/carshelter3.jpg"
        ],
        "name": "Jeepsy Half 2",
        "description": "Car shelter description for Shelter 2."
    }


]